{
  "updated_at": "2025-09-28T11:51:52.897455",
  "sources": {
    "imagem.jpg": {
      "updated_at": "2025-09-28T11:51:52.897455",
      "motos": [
        {
          "source": "imagem.jpg",
          "track_id": 1,
          "x": 542.36,
          "y": 437.72,
          "detected_at": "2025-09-28T11:51:52.690126",
          "db_id": 138,
          "run_id": "740d3ec9-892c-4864-9692-8f31e4eedf36"
        },
        {
          "source": "imagem.jpg",
          "track_id": 2,
          "x": 368.84,
          "y": 431.12,
          "detected_at": "2025-09-28T11:51:52.690126",
          "db_id": 139,
          "run_id": "740d3ec9-892c-4864-9692-8f31e4eedf36"
        },
        {
          "source": "imagem.jpg",
          "track_id": 3,
          "x": 180.54,
          "y": 422.65,
          "detected_at": "2025-09-28T11:51:52.690126",
          "db_id": 140,
          "run_id": "740d3ec9-892c-4864-9692-8f31e4eedf36"
        },
        {
          "source": "imagem.jpg",
          "track_id": 4,
          "x": 41.23,
          "y": 348.61,
          "detected_at": "2025-09-28T11:51:52.690126",
          "db_id": 141,
          "run_id": "740d3ec9-892c-4864-9692-8f31e4eedf36"
        },
        {
          "source": "imagem.jpg",
          "track_id": 5,
          "x": 741.49,
          "y": 425.3,
          "detected_at": "2025-09-28T11:51:52.690126",
          "db_id": 142,
          "run_id": "740d3ec9-892c-4864-9692-8f31e4eedf36"
        },
        {
          "source": "imagem.jpg",
          "track_id": 6,
          "x": 882.29,
          "y": 431.44,
          "detected_at": "2025-09-28T11:51:52.690126",
          "db_id": 143,
          "run_id": "740d3ec9-892c-4864-9692-8f31e4eedf36"
        }
      ]
    }
  },
  "run_id": "740d3ec9-892c-4864-9692-8f31e4eedf36"
}